mkdocs_meta_manager_plugin/__init__.py
mkdocs_meta_manager_plugin/plugin.py
mkdocs_meta_manager-1.1.0.dist-info/METADATA
mkdocs_meta_manager-1.1.0.dist-info/WHEEL
mkdocs_meta_manager-1.1.0.dist-info/entry_points.txt
mkdocs_meta_manager-1.1.0.dist-info/top_level.txt
mkdocs_meta_manager-1.1.0.dist-info/RECORD
